Metadata-Version: 2.1
Name: pd-to-mssql
Version: 0.2.1
Summary: Quick upload of pandas dataframes to Microsoft SQL Server
Home-page: https://github.com/veyron8800/pd_to_mssql
Author: Andrew Reis
Author-email: veyron8800@gmail.com
License: MIT
Download-URL: https://github.com/veyron8800/pd_to_mssql/archive/v0.2.1.tar.gz
Keywords: pandas,dataframe,mssql,sql,to_sql,df,pyodbc
Platform: UNKNOWN
Classifier: Development Status :: 4 - Beta
Classifier: Intended Audience :: Developers
Classifier: Topic :: Software Development :: Build Tools
Classifier: License :: OSI Approved :: MIT License
Classifier: Programming Language :: Python :: 3.7
Classifier: Programming Language :: Python :: 3.8
